coveo_arnparse/__init__.py
coveo_arnparse/py.typed
coveo_arnparse-1.0.12.dist-info/METADATA
coveo_arnparse-1.0.12.dist-info/WHEEL
coveo_arnparse-1.0.12.dist-info/RECORD
