Metadata-Version: 2.1
Name: coveo-arnparse
Version: 1.0.12
Summary: Parse an arn in multiple components.
Home-page: https://github.com/coveooss/coveo-python-oss/tree/main/coveo-arnparse
License: Apache-2.0
Author: Jonathan Piché
Author-email: tools@coveo.com
Requires-Python: >=3.8
Classifier: License :: OSI Approved :: Apache Software License
Classifier: Programming Language :: Python :: 3
Classifier: Programming Language :: Python :: 3.8
Classifier: Programming Language :: Python :: 3.9
Classifier: Programming Language :: Python :: 3.10
Classifier: Programming Language :: Python :: 3.11
Project-URL: Repository, https://github.com/coveooss/coveo-python-oss/tree/main/coveo-arnparse
